MUX.v
module MUX_Block(
input wire start_bit,
input wire ser_data,
input wire par_bit,
input wire stop_bit,
input wire [1:0] mux_sel,
output reg S_DATA
);
//Combinational always 
always @(*)
begin
    case(mux_sel)
      ('b00):S_DATA<=start_bit;
      ('b01):S_DATA<=ser_data;
      ('b10):S_DATA<=par_bit;
      ('b11):S_DATA<=stop_bit;
    endcase
end
endmodule

FSM.v
module FSM_Block (
    input wire ser_done,
    input wire PAR_EN,
    input wire Data_Valid,
    input wire CLK,RST ,
    output reg ser_en,
    output reg busy,
    output reg start_bit,
    output reg stop_bit,
    output reg [1:0] mux_sel
);
reg [4:0] current_state,next_state;
localparam [4:0] IDLE_STATE=5'b00001,
                START_STATE=5'b00010,
                DATA_STATE=5'b00100,
                PARITY_STATE=5'b01000,
                STOP_STATE=5'b10000;

//Sequential Block for State Transition 
always @(posedge CLK or negedge RST)
begin
    if(!RST)
        current_state<=IDLE_STATE;
    else
        current_state<=next_state;
end

//Combinational Always Block for Next State logic + Output logic
always @ (*)
 begin
    //default output values
    start_bit=1'b1;
    stop_bit=1'b0;
    ser_en=1'b0;
    busy=1'b0;
    mux_sel=2'b00;
   case(current_state)
    IDLE_STATE:
        begin
                start_bit=1'b1;
                stop_bit=1'b0;
                ser_en=1'b0;
                busy=1'b0;
                mux_sel=2'b00;
         if(!Data_Valid)
            begin
                next_state<=IDLE_STATE;
            end
         else
            begin
                next_state<=START_STATE;
            end
        end
    START_STATE:
        begin
                start_bit=1'b0;
                stop_bit=1'b0;
                ser_en=1'b0;
                busy=1'b1;
                mux_sel=2'b00;
                next_state<=DATA_STATE;
        end
    DATA_STATE:
        begin
                start_bit=1'b1;
                stop_bit=1'b0;
                busy=1'b1;
                ser_en=1'b1;
                mux_sel=2'b01;
            if(!ser_done)
                begin
                    next_state<=DATA_STATE;
                end
            else if(PAR_EN)
                begin
                        ser_en=1'b0;
                        mux_sel=2'b10;
                    next_state<=PARITY_STATE;
                end
            else
                begin
                                 ser_en=1'b0;
                        mux_sel=2'b11;
                    next_state<=STOP_STATE;
                end 
        end
    PARITY_STATE:
        begin
            start_bit=1'b1;
            stop_bit=1'b0;
            busy=1'b1;
            ser_en=1'b0;
            mux_sel=2'b10;
            next_state<=STOP_STATE;
        end
    STOP_STATE:
        begin
             start_bit=1'b1;
             stop_bit=1'b1;
             busy=1'b1;
             ser_en=1'b0;
             mux_sel=2'b11;
             if(!Data_Valid)
                next_state<=IDLE_STATE;
            else
                next_state<=START_STATE;
        end
    default:
        begin
                start_bit=1'b1;
                stop_bit=1'b0;
                ser_en=1'b0;
                busy=1'b0;
                mux_sel=2'b00;
                next_state<=IDLE_STATE;
        end
    endcase
 end
endmodule

Serializer.v
module serializer_block #(parameter IN_DATA_WIDTH=8)
(
  input wire [IN_DATA_WIDTH-1:0] P_DATA,
  input wire ser_en,
  input wire CLK,
  input wire RST,
  input wire Data_Valid,
  output reg ser_done,
  output reg ser_data
);
  reg [3:0] count_bits;
  reg [IN_DATA_WIDTH-1:0] input_store_comb;
  assign count_max =(count_bits==4'b1000);

always @(posedge CLK or negedge RST)
   begin
   if (!RST) 
    begin
      input_store_comb<='b0;
      ser_done<=1'b0;
      ser_data <= 1'b0;
      count_bits <= 4'b0;
    end
   else if(!ser_en && Data_Valid )
     begin
      input_store_comb <= P_DATA;
      ser_done<=1'b0;
    end
    else if( ser_en && !count_max)
     begin
        ser_done<=1'b0;
        ser_data <=input_store_comb>>(count_bits);
        count_bits<= count_bits+4'b1;
     end
     else if(count_max)
     begin
        ser_done<=1'b1;
        count_bits<=4'b0;
     end
     else
        begin
          ser_done<=1'b0;
        end
   end
endmodule

Parity_Calc.v
module parityCalc_block #(parameter IN_DATA_WIDTH=8)(
input wire [IN_DATA_WIDTH-1:0] P_DATA,
input wire Data_Valid,
input wire PAR_TYP,
output reg par_bit
);
always @(*)
begin
 if(Data_Valid)
  begin
   if(PAR_TYP==1'b0)
    par_bit<=(^P_DATA);
   else
    par_bit<=(~^P_DATA);
  end
 else
    par_bit<=par_bit;
end
endmodule

UART_TX_RTL.v
`include  "MUX.v"
`include "Parity_Calc.v"
`include "Serializer.v"
`include "FSM.v"
module UART_TX #(parameter P_DATA_WIDTH=8)
(
    input wire [P_DATA_WIDTH-1:0] P_DATA,
    input wire CLK,RST,
    input wire Data_Valid,
    input wire PAR_EN,PAR_TYP,
    output wire busy,
    output wire S_DATA
);
//Internal Signals
wire ser_done,ser_en,ser_data;
wire [1:0] mux_sel;
wire par_bit;
wire start_bit,stop_bit;

parityCalc_block #(.IN_DATA_WIDTH(P_DATA_WIDTH)) U0_Parity (
.P_DATA(P_DATA),
//.CLK(CLK),
.Data_Valid(Data_Valid),
.PAR_TYP(PAR_TYP),
.par_bit(par_bit)
);
serializer_block #(.IN_DATA_WIDTH(P_DATA_WIDTH)) U0_serializer(
.P_DATA(P_DATA),
.ser_en(ser_en),
.CLK(CLK),
.RST(RST),
.Data_Valid(Data_Valid),
.ser_done(ser_done),
.ser_data(ser_data)
);
FSM_Block U0_FSM(
.ser_done(ser_done),
.PAR_EN(PAR_EN),
.Data_Valid(Data_Valid),
.CLK(CLK),
.RST(RST),
.ser_en(ser_en),
.start_bit(start_bit),
.stop_bit(stop_bit),
.busy(busy),
.mux_sel(mux_sel)
);
MUX_Block U0_MUX(
.ser_data(ser_data),
.par_bit(par_bit),
.mux_sel(mux_sel),
.start_bit(start_bit),
.stop_bit(stop_bit),
.S_DATA(S_DATA)
);
endmodule

UART_TX_TB.v
`timescale 1us/1ns
`include "UART_TX_RTL.v"
module UART_TX_TB #(parameter P_DATA_WIDTH_TB=8) ();
//Defining INPUTS and OUTPUTS
reg [P_DATA_WIDTH_TB-1:0] P_DATA_TB;
reg Data_Valid_TB;
reg CLK_TB;
reg RST_TB;
reg PAR_EN_TB;
reg PAR_TYP_TB;
//Those 2 Output Signals to be checked for test cases
wire S_DATA_TB;
wire busy_TB;

parameter CLK_PERIOD=8.68;

//First Packet
parameter [P_DATA_WIDTH_TB-1:0] data_1 ='b01011010;
//Second Packet
parameter [P_DATA_WIDTH_TB-1:0] data_2='b01101011;

//INITIAL BLOCK

initial 
begin
    //System Commands
    $dumpfile("Output.vcd");
    $dumpvars;
    //Initialize 
    initialize();
    //No Parity
    parity_configuration(1'b0,1'b1);
    //Reset
    reset();
    
    load_parallel_data(data_1);
//Data Cycles
    check_serial_data(data_1);
//Busy Signal Activated during the data cycles
    check_busy_signal();
//Busy Signal is Activated during the Stop Cycle
    check_busy_signal();

    load_parallel_data(data_2);
//Data Cycles
    check_serial_data(data_2);
//Busy Signal Activated during the Data Cycles
    check_busy_signal();
//Busy Signal is Activated during the Stop Cycle
    check_busy_signal();

//Enabling Parity and choosing the type as odd
    parity_configuration(1'b1,1'b1);
    load_parallel_data(data_1);
//Data Cycles
    check_serial_data(data_1);
//Busy Signal Activated during the data cycles
    check_busy_signal();
//Busy Signal Activated during the Parity Cycle
    check_busy_signal();
//Busy Signal is Activated during the Stop Cycle
    check_busy_signal();

    load_parallel_data(data_2);
//Data Cycles
    check_serial_data(data_2);
//Busy Signal Activated during the data cycles
    check_busy_signal();
//Busy Signal Activated during the Parity Cycle
    check_busy_signal();
//Busy Signal is Activated during the Stop Cycle
    check_busy_signal();

    #CLK_PERIOD
    $finish;
end

//TASKS

//Initialization
task initialize;
begin
    Data_Valid_TB=1'b0;
    CLK_TB=1'b0;
    RST_TB=1'b1;
    P_DATA_TB='b0;
end
endtask
//Reset
task reset;
begin
    #CLK_PERIOD 
    RST_TB=1'b0;//100 low
    #CLK_PERIOD
    RST_TB=1'b1;//200 high
end
endtask

//Loading Parallel data
task load_parallel_data;
input [P_DATA_WIDTH_TB-1:0] p_data;
begin
Data_Valid_TB=1'b1;
#(CLK_PERIOD/2)
P_DATA_TB=p_data;
#(CLK_PERIOD/2)
Data_Valid_TB=1'b0;
P_DATA_TB='b0;
end
endtask

//Checking busy Signal
task check_busy_signal;
#CLK_PERIOD
if(busy_TB==1'b1)
    $display("Activated Busy Signal");
else
    $display("Deactivated Busy Signal");
endtask

//Checking Serial bits at Output
task check_serial_data;
integer count;
input [P_DATA_WIDTH_TB-1:0] p_data;
begin
    #CLK_PERIOD
    for(count=0;count<=P_DATA_WIDTH_TB-1;count=count+1)
    begin
        #CLK_PERIOD
        if(S_DATA_TB==p_data[count])
        $display("Bit number %d Succeeded = %b",count+1,S_DATA_TB);
        else
        $display("Bit number %d Failed = %b",count+1,S_DATA_TB);
    end
end
endtask
task parity_configuration;
input parity_enable;
input parity_type;
begin
    //Configuration make PAR_EN equal 1 if parity needed and 0 if not needed
    PAR_EN_TB=parity_enable;
    //Configuration make PAR_TYP equal 0 for even parity and 1 for odd parity
    PAR_TYP_TB=parity_type;
end
endtask

//CLOCK GENERATOR
always #(CLK_PERIOD/2) CLK_TB=~CLK_TB;
// Instantiation
UART_TX #(.P_DATA_WIDTH(P_DATA_WIDTH_TB)) DUT(
.P_DATA(P_DATA_TB),
.Data_Valid(Data_Valid_TB),
.PAR_EN(PAR_EN_TB),
.PAR_TYP(PAR_TYP_TB),
.CLK(CLK_TB),
.RST(RST_TB),
.S_DATA(S_DATA_TB),
.busy(busy_TB)
);
endmodule

Output.vcd
$date
	Mon Mar 18 22:41:25 2024
$end
$version
	Icarus Verilog
$end
$timescale
	1ns
$end
$scope module UART_TX_TB $end
$var wire 1 ! busy_TB $end
$var wire 1 " S_DATA_TB $end
$var real 1 # CLK_PERIOD $end
$var parameter 32 $ P_DATA_WIDTH_TB $end
$var parameter 8 % data_1 $end
$var parameter 8 & data_2 $end
$var reg 1 ' CLK_TB $end
$var reg 1 ( Data_Valid_TB $end
$var reg 1 ) PAR_EN_TB $end
$var reg 1 * PAR_TYP_TB $end
$var reg 8 + P_DATA_TB [7:0] $end
$var reg 1 , RST_TB $end
$scope module DUT $end
$var wire 1 ' CLK $end
$var wire 1 ( Data_Valid $end
$var wire 1 ) PAR_EN $end
$var wire 1 * PAR_TYP $end
$var wire 8 - P_DATA [7:0] $end
$var wire 1 , RST $end
$var wire 1 . stop_bit $end
$var wire 1 / start_bit $end
$var wire 1 0 ser_en $end
$var wire 1 1 ser_done $end
$var wire 1 2 ser_data $end
$var wire 1 3 par_bit $end
$var wire 2 4 mux_sel [1:0] $end
$var wire 1 ! busy $end
$var wire 1 " S_DATA $end
$var parameter 32 5 P_DATA_WIDTH $end
$scope module U0_FSM $end
$var wire 1 ' CLK $end
$var wire 1 ( Data_Valid $end
$var wire 1 ) PAR_EN $end
$var wire 1 , RST $end
$var wire 1 1 ser_done $end
$var parameter 5 6 DATA_STATE $end
$var parameter 5 7 IDLE_STATE $end
$var parameter 5 8 PARITY_STATE $end
$var parameter 5 9 START_STATE $end
$var parameter 5 : STOP_STATE $end
$var reg 1 ! busy $end
$var reg 5 ; current_state [4:0] $end
$var reg 2 < mux_sel [1:0] $end
$var reg 5 = next_state [4:0] $end
$var reg 1 0 ser_en $end
$var reg 1 / start_bit $end
$var reg 1 . stop_bit $end
$upscope $end
$scope module U0_MUX $end
$var wire 2 > mux_sel [1:0] $end
$var wire 1 / start_bit $end
$var wire 1 . stop_bit $end
$var wire 1 2 ser_data $end
$var wire 1 3 par_bit $end
$var reg 1 " S_DATA $end
$upscope $end
$scope module U0_Parity $end
$var wire 1 ( Data_Valid $end
$var wire 1 * PAR_TYP $end
$var wire 8 ? P_DATA [7:0] $end
$var parameter 32 @ IN_DATA_WIDTH $end
$var reg 1 3 par_bit $end
$upscope $end
$scope module U0_serializer $end
$var wire 1 ' CLK $end
$var wire 1 ( Data_Valid $end
$var wire 8 A P_DATA [7:0] $end
$var wire 1 , RST $end
$var wire 1 0 ser_en $end
$var wire 1 B count_max $end
$var parameter 32 C IN_DATA_WIDTH $end
$var reg 4 D count_bits [3:0] $end
$var reg 8 E input_store_comb [7:0] $end
$var reg 1 2 ser_data $end
$var reg 1 1 ser_done $end
$upscope $end
$upscope $end
$scope task check_busy_signal $end
$upscope $end
$scope task check_serial_data $end
$var reg 8 F p_data [7:0] $end
$var integer 32 G count [31:0] $end
$upscope $end
$scope task initialize $end
$upscope $end
$scope task load_parallel_data $end
$var reg 8 H p_data [7:0] $end
$upscope $end
$scope task parity_configuration $end
$var reg 1 I parity_enable $end
$var reg 1 J parity_type $end
$upscope $end
$scope task reset $end
$upscope $end
$upscope $end
$enddefinitions $end
$comment Show the parameter values. $end
$dumpall
b1000 C
b1000 @
b10000 :
b10 9
b1000 8
b1 7
b100 6
b1000 5
b1101011 &
b1011010 %
b1000 $
r8.68 #
$end
#0
$dumpvars
1J
0I
bx H
bx G
bx F
bx E
bx D
xB
b0 A
b0 ?
b0 >
b1 =
b0 <
bx ;
b0 4
x3
x2
x1
00
1/
0.
b0 -
1,
b0 +
1*
0)
0(
0'
1"
0!
$end
#4340
01
b1 ;
1'
#8680
0B
b0 D
02
b0 E
0'
0,
#13020
1'
#17360
b10 =
13
0'
1(
b1011010 H
1,
#21700
0"
b100 =
1!
0/
b10 ;
b1011010 E
1'
b1011010 +
b1011010 -
b1011010 ?
b1011010 A
#26040
1!
0/
0'
b1011010 F
b0 +
b0 -
b0 ?
b0 A
0(
#30380
b1 4
b1 <
b1 >
10
1!
1/
b100 ;
1'
#34720
0'
b0 G
#39060
b1 D
1'
#43400
0'
b1 G
#47740
1"
b10 D
12
1'
#52080
0'
b10 G
#56420
0"
b11 D
02
1'
#60760
0'
b11 G
#65100
1"
b100 D
12
1'
#69440
0'
b100 G
#73780
b101 D
1'
#78120
0'
b101 G
#82460
0"
b110 D
02
1'
#86800
0'
b110 G
#91140
1"
b111 D
12
1'
#95480
0'
b111 G
#99820
0"
1B
b1000 D
02
1'
#104160
0'
b1000 G
#108500
b10000 =
b11 4
b11 <
b11 >
1!
00
0B
b0 D
11
1'
#112840
0'
#117180
1"
b1 =
1.
b11 4
b11 <
b11 >
1!
01
b10000 ;
1'
#121520
b10 =
b11 4
b11 <
b11 >
1!
1.
0'
1(
b1101011 H
#125860
0"
b100 =
0/
b0 4
b0 <
b0 >
1!
0.
b10 ;
b1101011 E
03
1'
b1101011 +
b1101011 -
b1101011 ?
b1101011 A
#130200
1!
0/
0'
b1101011 F
b0 +
b0 -
b0 ?
b0 A
0(
#134540
b1 4
b1 <
b1 >
10
1!
1/
b100 ;
1'
#138880
0'
b0 G
#143220
1"
b1 D
12
1'
#147560
0'
b1 G
#151900
b10 D
1'
#156240
0'
b10 G
#160580
0"
b11 D
02
1'
#164920
0'
b11 G
#169260
1"
b100 D
12
1'
#173600
0'
b100 G
#177940
0"
b101 D
02
1'
#182280
0'
b101 G
#186620
1"
b110 D
12
1'
#190960
0'
b110 G
#195300
b111 D
1'
#199640
0'
b111 G
#203980
0"
1B
b1000 D
02
1'
#208320
0'
b1000 G
#212660
b10000 =
b11 4
b11 <
b11 >
1!
00
0B
b0 D
11
1'
#217000
0'
#221340
1"
b1 =
1.
b11 4
b11 <
b11 >
1!
01
b10000 ;
1'
#225680
13
b10 =
b11 4
b11 <
b11 >
1!
1.
0'
1(
b1011010 H
1)
1I
#230020
0"
b100 =
0/
b0 4
b0 <
b0 >
1!
0.
b10 ;
b1011010 E
1'
b1011010 +
b1011010 -
b1011010 ?
b1011010 A
#234360
1!
0/
0'
b1011010 F
b0 +
b0 -
b0 ?
b0 A
0(
#238700
b1 4
b1 <
b1 >
10
1!
1/
b100 ;
1'
#243040
0'
b0 G
#247380
b1 D
1'
#251720
0'
b1 G
#256060
1"
b10 D
12
1'
#260400
0'
b10 G
#264740
0"
b11 D
02
1'
#269080
0'
b11 G
#273420
1"
b100 D
12
1'
#277760
0'
b100 G
#282100
b101 D
1'
#286440
0'
b101 G
#290780
0"
b110 D
02
1'
#295120
0'
b110 G
#299460
1"
b111 D
12
1'
#303800
0'
b111 G
#308140
0"
1B
b1000 D
02
1'
#312480
0'
b1000 G
#316820
1"
b1000 =
b10 4
b10 <
b10 >
1!
00
0B
b0 D
11
1'
#321160
0'
#325500
b10000 =
b10 4
b10 <
b10 >
1!
01
b1000 ;
1'
#329840
0'
#334180
b1 =
1.
b11 4
b11 <
b11 >
1!
b10000 ;
1'
#338520
b10 =
b11 4
b11 <
b11 >
1!
1.
0'
1(
b1101011 H
#342860
0"
b100 =
0/
b0 4
b0 <
b0 >
1!
0.
b1101011 E
b10 ;
03
1'
b1101011 +
b1101011 -
b1101011 ?
b1101011 A
#347200
1!
0/
0'
b1101011 F
b0 +
b0 -
b0 ?
b0 A
0(
#351540
b1 4
b1 <
b1 >
10
1!
1/
b100 ;
1'
#355880
0'
b0 G
#360220
1"
b1 D
12
1'
#364560
0'
b1 G
#368900
b10 D
1'
#373240
0'
b10 G
#377580
0"
b11 D
02
1'
#381920
0'
b11 G
#386260
1"
b100 D
12
1'
#390600
0'
b100 G
#394940
0"
b101 D
02
1'
#399280
0'
b101 G
#403620
1"
b110 D
12
1'
#407960
0'
b110 G
#412300
b111 D
1'
#416640
0'
b111 G
#420980
0"
1B
b1000 D
02
1'
#425320
0'
b1000 G
#429660
b1000 =
b10 4
b10 <
b10 >
1!
00
0B
b0 D
11
1'
#434000
0'
#438340
b10000 =
b10 4
b10 <
b10 >
1!
b1000 ;
01
1'
#442680
0'
#447020
1"
b1 =
1.
b11 4
b11 <
b11 >
1!
b10000 ;
1'
#451360
0'
#455700
b0 4
b0 <
b0 >
0!
0.
b1 ;
1'
